pystamps/__init__.py
pystamps/pystamps.py
pystamps-0.1.0.dist-info/entry_points.txt
pystamps-0.1.0.dist-info/top_level.txt
pystamps-0.1.0.dist-info/METADATA
pystamps-0.1.0.dist-info/DESCRIPTION.rst
pystamps-0.1.0.dist-info/metadata.json
pystamps-0.1.0.dist-info/WHEEL
pystamps-0.1.0.dist-info/RECORD
